{"id":10236,"n":"D. Ieseanu","sn":"D. Ieseanu","cl":"-","tm":"-","pos":"Centre-Back","pg":"CB","age":25,"min":1049,"mp":14,"comp":"Romania. Liga II","lg":"Romania. Liga II","mv":null,"mvn":0,"nat":[],"dob":null,"pid":null,"m":{"Goals per 90":0.09,"xG per 90":0.08,"Shots per 90":0.51,"Shots on target, %":33.33,"xA per 90":0.03,"Crosses per 90":0.09,"Dribbles per 90":0.09,"Successful dribbles, %":100,"Offensive duels per 90":1.03,"Offensive duels won, %":41.67,"Touches in box per 90":0.77,"Defensive duels per 90":5.41,"Defensive duels won, %":66.67,"Aerial duels per 90":4.03,"Aerial duels won, %":55.32,"Interceptions per 90":4.46,"Successful defensive actions per 90":8.58,"Sliding tackles per 90":0.51,"Fouls per 90":1.12,"Shots blocked per 90":0.51},"p":{"Goals per 90":35,"xG per 90":57,"Shots per 90":47,"Shots on target, %":48,"xA per 90":63,"Crosses per 90":8,"Dribbles per 90":10,"Successful dribbles, %":77,"Offensive duels per 90":34,"Offensive duels won, %":39,"Touches in box per 90":60,"Defensive duels per 90":41,"Defensive duels won, %":25,"Aerial duels per 90":52,"Aerial duels won, %":39,"Interceptions per 90":36,"Successful defensive actions per 90":28,"Sliding tackles per 90":67,"Fouls per 90":33,"Shots blocked per 90":41},"gp":{"Goals per 90":53,"xG per 90":75,"Shots per 90":69,"Shots on target, %":41,"xA per 90":65,"Crosses per 90":13,"Dribbles per 90":11,"Successful dribbles, %":84,"Offensive duels per 90":33,"Offensive duels won, %":35,"Touches in box per 90":67,"Defensive duels per 90":57,"Defensive duels won, %":44,"Aerial duels per 90":53,"Aerial duels won, %":46,"Interceptions per 90":44,"Successful defensive actions per 90":52,"Sliding tackles per 90":82,"Fouls per 90":36,"Shots blocked per 90":40},"r":[{"key":"Defensive duels won, %","label":"Defensive Challenge %","value":66.67,"percentile":25,"invert":false},{"key":"Aerial duels won, %","label":"Aerial Duels Won %","value":55.32,"percentile":39,"invert":false},{"key":"Interceptions per 90","label":"Interceptions /90","value":4.46,"percentile":36,"invert":false},{"key":"Successful defensive actions per 90","label":"Ball Recoveries /90","value":8.58,"percentile":28,"invert":false},{"key":"Defensive duels per 90","label":"Defensive Duels /90","value":5.41,"percentile":41,"invert":false},{"key":"Fouls per 90","label":"Fouls /90","value":1.12,"percentile":33,"invert":true},{"key":"Shots blocked per 90","label":"Shots Blocked /90","value":0.51,"percentile":41,"invert":false}]}