{"id":10855,"n":"T. Knöll","sn":"T. Knöll","cl":"Al Ta'ee","tm":"Al Ta'ee","pos":"Centre-Forward","pg":"FW","age":28,"min":660,"mp":10,"comp":"Croatia. First NL","lg":"Croatia. First NL","mv":null,"mvn":0,"nat":[],"dob":null,"pid":null,"m":{"Goals per 90":0.68,"xG per 90":0.55,"Shots per 90":2.45,"Shots on target, %":55.56,"xA per 90":0.04,"Key passes per 90":0.27,"Crosses per 90":0.95,"Dribbles per 90":0.82,"Successful dribbles, %":83.33,"Offensive duels per 90":10.64,"Offensive duels won, %":29.49,"Touches in box per 90":3.55,"Progressive runs per 90":0.55,"Defensive duels per 90":3,"Defensive duels won, %":54.55,"Aerial duels per 90":4.77,"Aerial duels won, %":37.14,"Interceptions per 90":0.82,"Successful defensive actions per 90":2.45,"Fouls per 90":1.09,"Passes per 90":18.27,"Accurate passes, %":72.39,"Long passes per 90":1.36,"Accurate long passes, %":40,"Progressive passes per 90":0.95,"Accurate progressive passes, %":71.43,"Forward passes per 90":4.36,"Accurate forward passes, %":50,"Passes to final third per 90":1.91,"Passes to penalty area per 90":1.09,"Deep completions per 90":0.68,"Smart passes per 90":0.14},"p":{"Goals per 90":93,"xG per 90":94,"Shots per 90":75,"Shots on target, %":78,"xA per 90":26,"Key passes per 90":22,"Crosses per 90":33,"Dribbles per 90":8,"Successful dribbles, %":98,"Offensive duels per 90":67,"Offensive duels won, %":21,"Touches in box per 90":71,"Progressive runs per 90":10,"Defensive duels per 90":26,"Defensive duels won, %":36,"Aerial duels per 90":61,"Aerial duels won, %":71,"Interceptions per 90":4,"Successful defensive actions per 90":9,"Fouls per 90":66,"Passes per 90":33,"Accurate passes, %":70,"Long passes per 90":41,"Accurate long passes, %":48,"Progressive passes per 90":8,"Accurate progressive passes, %":59,"Forward passes per 90":33,"Accurate forward passes, %":24,"Passes to final third per 90":38,"Passes to penalty area per 90":23,"Deep completions per 90":40,"Smart passes per 90":29},"gp":{"Goals per 90":95,"xG per 90":94,"Shots per 90":79,"Shots on target, %":88,"xA per 90":22,"Key passes per 90":33,"Crosses per 90":37,"Dribbles per 90":11,"Successful dribbles, %":97,"Offensive duels per 90":70,"Offensive duels won, %":26,"Touches in box per 90":71,"Progressive runs per 90":16,"Defensive duels per 90":27,"Defensive duels won, %":39,"Aerial duels per 90":67,"Aerial duels won, %":59,"Interceptions per 90":6,"Successful defensive actions per 90":10,"Fouls per 90":61,"Passes per 90":41,"Accurate passes, %":46,"Long passes per 90":60,"Accurate long passes, %":27,"Progressive passes per 90":8,"Accurate progressive passes, %":57,"Forward passes per 90":43,"Accurate forward passes, %":16,"Passes to final third per 90":52,"Passes to penalty area per 90":30,"Deep completions per 90":43,"Smart passes per 90":49},"r":[{"key":"xG per 90","label":"xG /90","value":0.55,"percentile":94,"invert":false},{"key":"Goals per 90","label":"Goals /90","value":0.68,"percentile":93,"invert":false},{"key":"Shots on target, %","label":"Shots on Target %","value":55.56,"percentile":78,"invert":false},{"key":"Key passes per 90","label":"Chances Created /90","value":0.27,"percentile":22,"invert":false},{"key":"Successful dribbles, %","label":"Dribble Success %","value":83.33,"percentile":98,"invert":false},{"key":"Crosses per 90","label":"Crosses /90","value":0.95,"percentile":33,"invert":false},{"key":"Aerial duels won, %","label":"Aerial Duels Won %","value":37.14,"percentile":71,"invert":false},{"key":"xA per 90","label":"xA /90","value":0.04,"percentile":26,"invert":false}]}