{"id":1416,"n":"Jonathan Silva","sn":"Jonathan Silva","cl":"FC Crotone","tm":"Padova","pos":"Attacking Midfield","pg":"AM","age":21,"min":305,"mp":9,"comp":"Italy. Serie B","lg":"Italy Serie C Group C","mv":"€550k","mvn":550000,"nat":["Brazil","Italy"],"dob":"Date of birth/Age:","pid":"1074917","m":{"xG per 90":0.2,"Shots per 90":1.77,"Shots on target, %":50,"Crosses per 90":1.18,"Dribbles per 90":3.54,"Successful dribbles, %":58.33,"Offensive duels per 90":10.03,"Offensive duels won, %":32.35,"Touches in box per 90":2.36,"Progressive runs per 90":2.36,"Progressive passes per 90":4.72,"Accurate progressive passes, %":81.25,"Passes to final third per 90":1.18,"Passes to penalty area per 90":3.25,"Deep completions per 90":1.48,"Smart passes per 90":0.3,"Accurate crosses, %":75},"p":{"xG per 90":56,"Shots per 90":46,"Shots on target, %":88,"Crosses per 90":25,"Dribbles per 90":54,"Successful dribbles, %":56,"Offensive duels per 90":51,"Offensive duels won, %":16,"Touches in box per 90":43,"Progressive runs per 90":66,"Progressive passes per 90":69,"Accurate progressive passes, %":72,"Passes to final third per 90":4,"Passes to penalty area per 90":69,"Deep completions per 90":73,"Smart passes per 90":76,"Accurate crosses, %":94},"gp":{"xG per 90":65,"Shots per 90":58,"Shots on target, %":84,"Crosses per 90":38,"Dribbles per 90":77,"Successful dribbles, %":67,"Offensive duels per 90":74,"Offensive duels won, %":19,"Touches in box per 90":60,"Progressive runs per 90":81,"Progressive passes per 90":55,"Accurate progressive passes, %":81,"Passes to final third per 90":4,"Passes to penalty area per 90":80,"Deep completions per 90":85,"Smart passes per 90":71,"Accurate crosses, %":96},"r":[{"key":"Shots per 90","label":"Shots /90","value":1.77,"percentile":46,"invert":false},{"key":"Touches in box per 90","label":"Box Touches /90","value":2.36,"percentile":43,"invert":false},{"key":"Passes to final third per 90","label":"Final Third Passes /90","value":1.18,"percentile":4,"invert":false},{"key":"Dribbles per 90","label":"Dribbles /90","value":3.54,"percentile":54,"invert":false},{"key":"Successful dribbles, %","label":"Dribble Success %","value":58.33,"percentile":56,"invert":false}]}