{"id":1718,"n":"Matteo Maggio","sn":"M. Maggio","cl":"FC Crotone","tm":"Crotone","pos":"Left Winger","pg":"FW","age":24,"min":1864,"mp":27,"comp":"Italy. Serie C","lg":"Italy Serie C Group C","mv":"€500k","mvn":500000,"nat":["Italy"],"dob":"06/01/2002 (24)","pid":"936646","m":{"Passes per 90":27.04,"Accurate passes, %":71.61,"Long passes per 90":1.4,"Accurate long passes, %":55.17,"Forward passes per 90":4.78,"Accurate forward passes, %":56.57},"p":{"Passes per 90":86,"Accurate passes, %":30,"Long passes per 90":70,"Accurate long passes, %":55,"Forward passes per 90":63,"Accurate forward passes, %":30},"gp":{"Passes per 90":80,"Accurate passes, %":41,"Long passes per 90":62,"Accurate long passes, %":63,"Forward passes per 90":50,"Accurate forward passes, %":34},"r":[]}