{"id":1800,"n":"Marcus Haglind-Sangré","sn":"M. Haglind-Sangré","cl":"Wisla Plock","tm":"Wisła Płock","pos":"Centre-Back","pg":"CB","age":31,"min":2068,"mp":21,"comp":"Poland. Ekstraklasa","lg":"Poland Ekstraklasa","mv":"€450k","mvn":450000,"nat":["Sweden"],"dob":"04/02/1995 (31)","pid":"221074","m":{"xG per 90":0.03,"Shots per 90":0.35,"Assists per 90":0.09,"xA per 90":0.02,"Key passes per 90":0.17,"Crosses per 90":1.04,"Dribbles per 90":0.3,"Successful dribbles, %":57.14,"Offensive duels per 90":1.91,"Offensive duels won, %":34.09,"Touches in box per 90":0.7,"Progressive runs per 90":0.83,"Passes per 90":38.12,"Accurate passes, %":84.13,"Long passes per 90":4.7,"Accurate long passes, %":47.22,"Progressive passes per 90":7.62,"Accurate progressive passes, %":62.86,"Forward passes per 90":16.71,"Accurate forward passes, %":75.52,"Passes to final third per 90":4.87,"Passes to penalty area per 90":0.87,"Deep completions per 90":0.17,"Accurate crosses, %":37.5},"p":{"xG per 90":16,"Shots per 90":33,"Assists per 90":79,"xA per 90":42,"Key passes per 90":71,"Crosses per 90":88,"Dribbles per 90":61,"Successful dribbles, %":34,"Offensive duels per 90":82,"Offensive duels won, %":19,"Touches in box per 90":25,"Progressive runs per 90":46,"Passes per 90":27,"Accurate passes, %":24,"Long passes per 90":51,"Accurate long passes, %":38,"Progressive passes per 90":68,"Accurate progressive passes, %":44,"Forward passes per 90":47,"Accurate forward passes, %":48,"Passes to final third per 90":46,"Passes to penalty area per 90":69,"Deep completions per 90":18,"Accurate crosses, %":42},"gp":{"xG per 90":29,"Shots per 90":43,"Assists per 90":67,"xA per 90":46,"Key passes per 90":74,"Crosses per 90":88,"Dribbles per 90":53,"Successful dribbles, %":34,"Offensive duels per 90":71,"Offensive duels won, %":17,"Touches in box per 90":61,"Progressive runs per 90":56,"Passes per 90":37,"Accurate passes, %":41,"Long passes per 90":30,"Accurate long passes, %":28,"Progressive passes per 90":48,"Accurate progressive passes, %":28,"Forward passes per 90":44,"Accurate forward passes, %":60,"Passes to final third per 90":42,"Passes to penalty area per 90":65,"Deep completions per 90":32,"Accurate crosses, %":40},"r":[{"key":"Accurate passes, %","label":"Pass Accuracy %","value":84.13,"percentile":24,"invert":false},{"key":"Long passes per 90","label":"Long Passes /90","value":4.7,"percentile":51,"invert":false},{"key":"Accurate long passes, %","label":"Long Pass Success %","value":47.22,"percentile":38,"invert":false}]}