{"id":225,"n":"Meriton Korenica","sn":"M. Korenica","cl":"CFR Cluj","tm":"CFR Cluj","pos":"Left Winger","pg":"FW","age":29,"min":1732,"mp":24,"comp":"Romania. Superliga","lg":"Romania Liga 1","mv":"€2.40m","mvn":2400000,"nat":["Kosovo"],"dob":"15/12/1996 (29)","pid":"412024","m":{"Goals per 90":0.36,"xG per 90":0.23,"Shots per 90":2.08,"Shots on target, %":47.5,"Assists per 90":0.05,"xA per 90":0.17,"Key passes per 90":0.52,"Crosses per 90":1.97,"Dribbles per 90":3.12,"Successful dribbles, %":58.33,"Offensive duels per 90":8.73,"Offensive duels won, %":41.07,"Touches in box per 90":1.97,"Progressive runs per 90":1.56,"Defensive duels per 90":4.88,"Defensive duels won, %":61.7,"Aerial duels per 90":2.96,"Aerial duels won, %":28.07,"Interceptions per 90":3.53,"Successful defensive actions per 90":7.48,"Sliding tackles per 90":0.94,"Fouls per 90":0.99,"Passes per 90":34.45,"Accurate passes, %":77.68,"Long passes per 90":2.29,"Accurate long passes, %":59.09,"Progressive passes per 90":5.2,"Accurate progressive passes, %":78,"Forward passes per 90":10.44,"Accurate forward passes, %":70.15,"Passes to final third per 90":4.26,"Passes to penalty area per 90":3.01,"Deep completions per 90":0.78,"Smart passes per 90":0.05,"Shots blocked per 90":0.21},"p":{"Goals per 90":65,"xG per 90":45,"Shots per 90":68,"Shots on target, %":74,"Assists per 90":6,"xA per 90":79,"Key passes per 90":67,"Crosses per 90":73,"Dribbles per 90":62,"Successful dribbles, %":65,"Offensive duels per 90":44,"Offensive duels won, %":77,"Touches in box per 90":13,"Progressive runs per 90":62,"Defensive duels per 90":64,"Defensive duels won, %":64,"Aerial duels per 90":40,"Aerial duels won, %":28,"Interceptions per 90":93,"Successful defensive actions per 90":89,"Sliding tackles per 90":97,"Fouls per 90":51,"Passes per 90":89,"Accurate passes, %":73,"Long passes per 90":82,"Accurate long passes, %":75,"Progressive passes per 90":90,"Accurate progressive passes, %":78,"Forward passes per 90":90,"Accurate forward passes, %":87,"Passes to final third per 90":92,"Passes to penalty area per 90":87,"Deep completions per 90":43,"Smart passes per 90":10,"Shots blocked per 90":70},"gp":{"Goals per 90":67,"xG per 90":50,"Shots per 90":65,"Shots on target, %":72,"Assists per 90":3,"xA per 90":84,"Key passes per 90":72,"Crosses per 90":66,"Dribbles per 90":63,"Successful dribbles, %":68,"Offensive duels per 90":47,"Offensive duels won, %":72,"Touches in box per 90":19,"Progressive runs per 90":59,"Defensive duels per 90":67,"Defensive duels won, %":69,"Aerial duels per 90":44,"Aerial duels won, %":30,"Interceptions per 90":94,"Successful defensive actions per 90":91,"Sliding tackles per 90":97,"Fouls per 90":67,"Passes per 90":94,"Accurate passes, %":76,"Long passes per 90":84,"Accurate long passes, %":70,"Progressive passes per 90":88,"Accurate progressive passes, %":77,"Forward passes per 90":94,"Accurate forward passes, %":83,"Passes to final third per 90":93,"Passes to penalty area per 90":81,"Deep completions per 90":50,"Smart passes per 90":4,"Shots blocked per 90":69},"r":[{"key":"xG per 90","label":"xG /90","value":0.23,"percentile":45,"invert":false},{"key":"Goals per 90","label":"Goals /90","value":0.36,"percentile":65,"invert":false},{"key":"Shots on target, %","label":"Shots on Target %","value":47.5,"percentile":74,"invert":false},{"key":"Key passes per 90","label":"Chances Created /90","value":0.52,"percentile":67,"invert":false},{"key":"Successful dribbles, %","label":"Dribble Success %","value":58.33,"percentile":65,"invert":false},{"key":"Crosses per 90","label":"Crosses /90","value":1.97,"percentile":73,"invert":false},{"key":"Aerial duels won, %","label":"Aerial Duels Won %","value":28.07,"percentile":28,"invert":false},{"key":"xA per 90","label":"xA /90","value":0.17,"percentile":79,"invert":false}]}