{"id":2444,"n":"Giacomo Parigi","sn":"G. Parigi","cl":"Latina Calcio 1932","tm":"Latina","pos":"Centre-Forward","pg":"FW","age":29,"min":2499,"mp":26,"comp":"Italy. Serie C","lg":"Italy Serie C Group C","mv":"€350k","mvn":350000,"nat":["Italy"],"dob":"18/06/1996 (29)","pid":"254708","m":{"Goals per 90":0.36,"xG per 90":0.32,"Shots per 90":2.52,"Shots on target, %":38.57,"Assists per 90":0.07,"xA per 90":0.06,"Key passes per 90":0.18,"Crosses per 90":0.76,"Dribbles per 90":1.04,"Successful dribbles, %":37.93,"Offensive duels per 90":8.28,"Offensive duels won, %":32.17,"Touches in box per 90":3.28,"Progressive runs per 90":0.36,"Progressive passes per 90":1.87,"Accurate progressive passes, %":61.54,"Passes to final third per 90":2.16,"Passes to penalty area per 90":0.83,"Deep completions per 90":0.65,"Accurate crosses, %":14.29,"Goal conversion, %":14.29},"p":{"Goals per 90":75,"xG per 90":75,"Shots per 90":84,"Shots on target, %":51,"Assists per 90":17,"xA per 90":46,"Key passes per 90":24,"Crosses per 90":42,"Dribbles per 90":22,"Successful dribbles, %":14,"Offensive duels per 90":37,"Offensive duels won, %":43,"Touches in box per 90":73,"Progressive runs per 90":13,"Progressive passes per 90":41,"Accurate progressive passes, %":34,"Passes to final third per 90":70,"Passes to penalty area per 90":26,"Deep completions per 90":47,"Accurate crosses, %":9,"Goal conversion, %":53},"gp":{"Goals per 90":67,"xG per 90":70,"Shots per 90":81,"Shots on target, %":48,"Assists per 90":13,"xA per 90":36,"Key passes per 90":16,"Crosses per 90":30,"Dribbles per 90":16,"Successful dribbles, %":13,"Offensive duels per 90":42,"Offensive duels won, %":37,"Touches in box per 90":63,"Progressive runs per 90":8,"Progressive passes per 90":32,"Accurate progressive passes, %":30,"Passes to final third per 90":60,"Passes to penalty area per 90":19,"Deep completions per 90":40,"Accurate crosses, %":6,"Goal conversion, %":48},"r":[{"key":"Crosses per 90","label":"Crosses /90","value":0.76,"percentile":42,"invert":false},{"key":"Accurate crosses, %","label":"Cross Success %","value":14.29,"percentile":9,"invert":false},{"key":"Goals per 90","label":"Goals /90","value":0.36,"percentile":75,"invert":false},{"key":"Shots per 90","label":"Shots /90","value":2.52,"percentile":84,"invert":false},{"key":"Shots on target, %","label":"Shots on Target %","value":38.57,"percentile":51,"invert":false},{"key":"Goal conversion, %","label":"Goal Conversion %","value":14.29,"percentile":53,"invert":false},{"key":"Touches in box per 90","label":"Box Touches /90","value":3.28,"percentile":73,"invert":false},{"key":"Assists per 90","label":"Assists /90","value":0.07,"percentile":17,"invert":false},{"key":"Key passes per 90","label":"Key Passes /90","value":0.18,"percentile":24,"invert":false},{"key":"Passes to final third per 90","label":"Final Third Passes /90","value":2.16,"percentile":70,"invert":false},{"key":"Dribbles per 90","label":"Dribbles /90","value":1.04,"percentile":22,"invert":false},{"key":"Successful dribbles, %","label":"Dribble Success %","value":37.93,"percentile":14,"invert":false}]}