{"id":2763,"n":"Matija Horvat","sn":"M. Horvat","cl":"Admira Wacker","tm":"Admira","pos":"Centre-Back","pg":"CB","age":26,"min":1004,"mp":11,"comp":"Austria. 2. Liga","lg":"Austria 2. Liga","mv":"€300k","mvn":300000,"nat":["Croatia"],"dob":"07/05/1999 (26)","pid":"338855","m":{"Goals per 90":0.09,"xG per 90":0.06,"Shots per 90":0.81,"Shots on target, %":22.22,"Assists per 90":0.18,"xA per 90":0.09,"Key passes per 90":0.18,"Crosses per 90":0.81,"Dribbles per 90":0.18,"Successful dribbles, %":100,"Offensive duels per 90":2.06,"Offensive duels won, %":39.13,"Touches in box per 90":1.61,"Progressive runs per 90":1.17,"Defensive duels per 90":5.56,"Defensive duels won, %":62.9,"Aerial duels per 90":2.96,"Aerial duels won, %":51.52,"Interceptions per 90":3.94,"Successful defensive actions per 90":7.62,"Sliding tackles per 90":0.18,"Fouls per 90":1.08,"Passes per 90":39.71,"Accurate passes, %":81.94,"Long passes per 90":7.53,"Accurate long passes, %":51.19,"Progressive passes per 90":7.35,"Accurate progressive passes, %":74.39,"Forward passes per 90":14.7,"Accurate forward passes, %":65.85,"Passes to final third per 90":6.81,"Passes to penalty area per 90":1.17,"Deep completions per 90":0.45,"Shots blocked per 90":0.27},"p":{"Goals per 90":47,"xG per 90":54,"Shots per 90":93,"Shots on target, %":26,"Assists per 90":92,"xA per 90":98,"Key passes per 90":69,"Crosses per 90":86,"Dribbles per 90":32,"Successful dribbles, %":79,"Offensive duels per 90":69,"Offensive duels won, %":38,"Touches in box per 90":95,"Progressive runs per 90":84,"Defensive duels per 90":53,"Defensive duels won, %":8,"Aerial duels per 90":15,"Aerial duels won, %":34,"Interceptions per 90":20,"Successful defensive actions per 90":16,"Sliding tackles per 90":17,"Fouls per 90":28,"Passes per 90":40,"Accurate passes, %":50,"Long passes per 90":68,"Accurate long passes, %":54,"Progressive passes per 90":27,"Accurate progressive passes, %":88,"Forward passes per 90":21,"Accurate forward passes, %":28,"Passes to final third per 90":63,"Passes to penalty area per 90":73,"Deep completions per 90":84,"Shots blocked per 90":17},"gp":{"Goals per 90":53,"xG per 90":60,"Shots per 90":91,"Shots on target, %":16,"Assists per 90":92,"xA per 90":96,"Key passes per 90":77,"Crosses per 90":83,"Dribbles per 90":33,"Successful dribbles, %":84,"Offensive duels per 90":75,"Offensive duels won, %":27,"Touches in box per 90":97,"Progressive runs per 90":76,"Defensive duels per 90":60,"Defensive duels won, %":25,"Aerial duels per 90":20,"Aerial duels won, %":31,"Interceptions per 90":24,"Successful defensive actions per 90":30,"Sliding tackles per 90":31,"Fouls per 90":39,"Passes per 90":43,"Accurate passes, %":28,"Long passes per 90":81,"Accurate long passes, %":46,"Progressive passes per 90":43,"Accurate progressive passes, %":80,"Forward passes per 90":26,"Accurate forward passes, %":14,"Passes to final third per 90":76,"Passes to penalty area per 90":80,"Deep completions per 90":84,"Shots blocked per 90":11},"r":[{"key":"Defensive duels won, %","label":"Defensive Challenge %","value":62.9,"percentile":8,"invert":false},{"key":"Aerial duels won, %","label":"Aerial Duels Won %","value":51.52,"percentile":34,"invert":false},{"key":"Accurate passes, %","label":"Pass Accuracy %","value":81.94,"percentile":50,"invert":false},{"key":"Interceptions per 90","label":"Interceptions /90","value":3.94,"percentile":20,"invert":false},{"key":"Successful defensive actions per 90","label":"Ball Recoveries /90","value":7.62,"percentile":16,"invert":false},{"key":"Defensive duels per 90","label":"Defensive Duels /90","value":5.56,"percentile":53,"invert":false},{"key":"Fouls per 90","label":"Fouls /90","value":1.08,"percentile":28,"invert":true},{"key":"Shots blocked per 90","label":"Shots Blocked /90","value":0.27,"percentile":17,"invert":false}]}