{"id":3068,"n":"Jakub Uhrincat","sn":"J. Uhrinčať","cl":"FC Hradec Kralove","tm":"Hradec Králové","pos":"Centre-Back","pg":"CB","age":25,"min":545,"mp":10,"comp":"Czech Republic. Chance Liga","lg":"Czech 1. Liga","mv":"€300k","mvn":300000,"nat":["Slovakia"],"dob":"07/02/2001 (24)","pid":"804553","m":{"xG per 90":0.01,"Shots per 90":0.33,"Shots on target, %":100,"xA per 90":0.11,"Key passes per 90":0.17,"Crosses per 90":0.83,"Dribbles per 90":0.33,"Successful dribbles, %":50,"Offensive duels per 90":1.32,"Offensive duels won, %":37.5,"Touches in box per 90":0.5,"Progressive runs per 90":0.66,"Progressive passes per 90":7.27,"Accurate progressive passes, %":54.55,"Passes to final third per 90":4.29,"Passes to penalty area per 90":1.32,"Deep completions per 90":0.17},"p":{"xG per 90":7,"Shots per 90":42,"Shots on target, %":96,"xA per 90":99,"Key passes per 90":60,"Crosses per 90":83,"Dribbles per 90":63,"Successful dribbles, %":24,"Offensive duels per 90":38,"Offensive duels won, %":25,"Touches in box per 90":28,"Progressive runs per 90":48,"Progressive passes per 90":52,"Accurate progressive passes, %":3,"Passes to final third per 90":32,"Passes to penalty area per 90":72,"Deep completions per 90":17},"gp":{"xG per 90":6,"Shots per 90":40,"Shots on target, %":97,"xA per 90":98,"Key passes per 90":74,"Crosses per 90":84,"Dribbles per 90":58,"Successful dribbles, %":22,"Offensive duels per 90":47,"Offensive duels won, %":24,"Touches in box per 90":39,"Progressive runs per 90":44,"Progressive passes per 90":41,"Accurate progressive passes, %":9,"Passes to final third per 90":30,"Passes to penalty area per 90":84,"Deep completions per 90":32},"r":[]}