{"id":3966,"n":"Ivan Saric","sn":"I. Šarić","cl":"FK Velez Mostar","tm":"Velež","pos":"Left Winger","pg":"FW","age":25,"min":1254,"mp":17,"comp":"Bosnia and Herzegovina. Premijer Liga","lg":"Bosnia Premier Liga","mv":"€250k","mvn":250000,"nat":["Croatia"],"dob":"16/01/2001 (25)","pid":"491046","m":{"Goals per 90":0.22,"xG per 90":0.28,"Shots per 90":1.44,"Shots on target, %":50,"xA per 90":0.07,"Key passes per 90":0.14,"Crosses per 90":0.86,"Dribbles per 90":1.22,"Successful dribbles, %":47.06,"Offensive duels per 90":8.33,"Offensive duels won, %":31.03,"Touches in box per 90":2.3,"Progressive runs per 90":0.86,"Defensive duels per 90":4.95,"Defensive duels won, %":68.12,"Aerial duels per 90":2.8,"Aerial duels won, %":23.08,"Interceptions per 90":1.79,"Successful defensive actions per 90":5.17,"Fouls per 90":1.36,"Passes per 90":18.23,"Accurate passes, %":72.83,"Long passes per 90":1.08,"Accurate long passes, %":33.33,"Progressive passes per 90":1.94,"Accurate progressive passes, %":74.07,"Forward passes per 90":3.8,"Accurate forward passes, %":58.49,"Passes to final third per 90":2.08,"Passes to penalty area per 90":1.58,"Deep completions per 90":0.65,"Smart passes per 90":0.07,"Shots blocked per 90":0.07},"p":{"Goals per 90":53,"xG per 90":79,"Shots per 90":53,"Shots on target, %":69,"xA per 90":45,"Key passes per 90":6,"Crosses per 90":37,"Dribbles per 90":38,"Successful dribbles, %":34,"Offensive duels per 90":56,"Offensive duels won, %":32,"Touches in box per 90":56,"Progressive runs per 90":47,"Defensive duels per 90":65,"Defensive duels won, %":83,"Aerial duels per 90":43,"Aerial duels won, %":10,"Interceptions per 90":29,"Successful defensive actions per 90":62,"Fouls per 90":49,"Passes per 90":48,"Accurate passes, %":58,"Long passes per 90":44,"Accurate long passes, %":28,"Progressive passes per 90":23,"Accurate progressive passes, %":65,"Forward passes per 90":24,"Accurate forward passes, %":48,"Passes to final third per 90":44,"Passes to penalty area per 90":52,"Deep completions per 90":57,"Smart passes per 90":17,"Shots blocked per 90":10},"gp":{"Goals per 90":37,"xG per 90":62,"Shots per 90":31,"Shots on target, %":78,"xA per 90":44,"Key passes per 90":8,"Crosses per 90":34,"Dribbles per 90":21,"Successful dribbles, %":31,"Offensive duels per 90":43,"Offensive duels won, %":33,"Touches in box per 90":29,"Progressive runs per 90":30,"Defensive duels per 90":69,"Defensive duels won, %":87,"Aerial duels per 90":42,"Aerial duels won, %":17,"Interceptions per 90":44,"Successful defensive actions per 90":65,"Fouls per 90":43,"Passes per 90":41,"Accurate passes, %":49,"Long passes per 90":48,"Accurate long passes, %":16,"Progressive passes per 90":33,"Accurate progressive passes, %":65,"Forward passes per 90":33,"Accurate forward passes, %":42,"Passes to final third per 90":58,"Passes to penalty area per 90":47,"Deep completions per 90":40,"Smart passes per 90":14,"Shots blocked per 90":11},"r":[{"key":"xG per 90","label":"xG /90","value":0.28,"percentile":79,"invert":false},{"key":"Goals per 90","label":"Goals /90","value":0.22,"percentile":53,"invert":false},{"key":"Shots on target, %","label":"Shots on Target %","value":50,"percentile":69,"invert":false},{"key":"Key passes per 90","label":"Chances Created /90","value":0.14,"percentile":6,"invert":false},{"key":"Successful dribbles, %","label":"Dribble Success %","value":47.06,"percentile":34,"invert":false},{"key":"Crosses per 90","label":"Crosses /90","value":0.86,"percentile":37,"invert":false},{"key":"Aerial duels won, %","label":"Aerial Duels Won %","value":23.08,"percentile":10,"invert":false},{"key":"xA per 90","label":"xA /90","value":0.07,"percentile":45,"invert":false}]}