{"id":5460,"n":"Petr Heppner","sn":"P. Heppner","cl":"FC SILON Taborsko","tm":"Táborsko","pos":"Left-Back","pg":"WB","age":28,"min":1317,"mp":16,"comp":"Czech Republic. Chance National Liga","lg":"Czech 2. Liga","mv":"€175k","mvn":175000,"nat":["Czech Republic"],"dob":"11/05/1997 (28)","pid":"568273","m":{"Goals per 90":0.27,"xG per 90":0.06,"Shots per 90":0.82,"Shots on target, %":33.33,"xA per 90":0.01,"Key passes per 90":0.07,"Crosses per 90":1.71,"Dribbles per 90":0.96,"Successful dribbles, %":64.29,"Offensive duels per 90":2.67,"Offensive duels won, %":46.15,"Touches in box per 90":0.96,"Progressive runs per 90":0.75,"Defensive duels per 90":4.72,"Defensive duels won, %":65.22,"Aerial duels per 90":3.83,"Aerial duels won, %":57.14,"Interceptions per 90":3.35,"Successful defensive actions per 90":6.77,"Sliding tackles per 90":0.34,"Fouls per 90":0.82,"Passes per 90":24.87,"Accurate passes, %":73.35,"Long passes per 90":4.24,"Accurate long passes, %":51.61,"Progressive passes per 90":5.81,"Accurate progressive passes, %":58.82,"Forward passes per 90":9.98,"Accurate forward passes, %":60.96,"Passes to final third per 90":2.73,"Passes to penalty area per 90":2.05,"Deep completions per 90":0.14,"Shots blocked per 90":0.34},"p":{"Goals per 90":83,"xG per 90":56,"Shots per 90":65,"Shots on target, %":38,"xA per 90":6,"Key passes per 90":2,"Crosses per 90":21,"Dribbles per 90":27,"Successful dribbles, %":59,"Offensive duels per 90":19,"Offensive duels won, %":61,"Touches in box per 90":33,"Progressive runs per 90":10,"Defensive duels per 90":10,"Defensive duels won, %":44,"Aerial duels per 90":81,"Aerial duels won, %":71,"Interceptions per 90":30,"Successful defensive actions per 90":13,"Sliding tackles per 90":62,"Fouls per 90":54,"Passes per 90":5,"Accurate passes, %":44,"Long passes per 90":47,"Accurate long passes, %":60,"Progressive passes per 90":24,"Accurate progressive passes, %":8,"Forward passes per 90":24,"Accurate forward passes, %":24,"Passes to final third per 90":8,"Passes to penalty area per 90":18,"Deep completions per 90":5,"Shots blocked per 90":69},"gp":{"Goals per 90":93,"xG per 90":69,"Shots per 90":74,"Shots on target, %":54,"xA per 90":4,"Key passes per 90":3,"Crosses per 90":27,"Dribbles per 90":30,"Successful dribbles, %":66,"Offensive duels per 90":21,"Offensive duels won, %":55,"Touches in box per 90":56,"Progressive runs per 90":18,"Defensive duels per 90":10,"Defensive duels won, %":62,"Aerial duels per 90":89,"Aerial duels won, %":78,"Interceptions per 90":25,"Successful defensive actions per 90":15,"Sliding tackles per 90":55,"Fouls per 90":68,"Passes per 90":9,"Accurate passes, %":35,"Long passes per 90":46,"Accurate long passes, %":67,"Progressive passes per 90":18,"Accurate progressive passes, %":13,"Forward passes per 90":15,"Accurate forward passes, %":24,"Passes to final third per 90":10,"Passes to penalty area per 90":34,"Deep completions per 90":5,"Shots blocked per 90":66},"r":[{"key":"Defensive duels won, %","label":"Defensive 1v1 %","value":65.22,"percentile":44,"invert":false},{"key":"Successful defensive actions per 90","label":"Defensive Actions /90","value":6.77,"percentile":13,"invert":false},{"key":"Aerial duels won, %","label":"Aerial Duels %","value":57.14,"percentile":71,"invert":false},{"key":"Crosses per 90","label":"Crosses /90","value":1.71,"percentile":21,"invert":false},{"key":"Successful dribbles, %","label":"Dribble Success %","value":64.29,"percentile":59,"invert":false},{"key":"Key passes per 90","label":"Chances Created /90","value":0.07,"percentile":2,"invert":false},{"key":"xA per 90","label":"xA /90","value":0.01,"percentile":6,"invert":false},{"key":"Fouls per 90","label":"Fouls /90","value":0.82,"percentile":54,"invert":true}]}