{"id":5654,"n":"Murat Bajraj","sn":"M. Bajraj","cl":"ND Beltinci","tm":"Beltinci","pos":"Centre-Forward","pg":"FW","age":25,"min":1084,"mp":16,"comp":"Slovenia. 2. SNL","lg":"Slovenia 2. SNL","mv":"€175k","mvn":175000,"nat":["Slovenia","Kosovo"],"dob":"08/07/2000 (25)","pid":"977990","m":{"Goals per 90":1,"xG per 90":0.9,"Shots per 90":4.07,"Shots on target, %":53.06,"xA per 90":0.06,"Key passes per 90":0.25,"Crosses per 90":1,"Dribbles per 90":2.32,"Successful dribbles, %":67.86,"Offensive duels per 90":7.89,"Offensive duels won, %":40,"Touches in box per 90":5.06,"Progressive runs per 90":1.08,"Passes per 90":11.96,"Accurate passes, %":66.67,"Long passes per 90":0.66,"Accurate long passes, %":62.5,"Progressive passes per 90":1.99,"Accurate progressive passes, %":79.17,"Forward passes per 90":2.74,"Accurate forward passes, %":66.67,"Passes to final third per 90":1.41,"Passes to penalty area per 90":1.25,"Deep completions per 90":0.5,"Smart passes per 90":0.17,"Accurate crosses, %":41.67,"Goal conversion, %":24.49},"p":{"Goals per 90":99,"xG per 90":97,"Shots per 90":97,"Shots on target, %":81,"xA per 90":28,"Key passes per 90":34,"Crosses per 90":40,"Dribbles per 90":37,"Successful dribbles, %":81,"Offensive duels per 90":25,"Offensive duels won, %":58,"Touches in box per 90":95,"Progressive runs per 90":39,"Passes per 90":6,"Accurate passes, %":16,"Long passes per 90":16,"Accurate long passes, %":82,"Progressive passes per 90":32,"Accurate progressive passes, %":78,"Forward passes per 90":11,"Accurate forward passes, %":81,"Passes to final third per 90":26,"Passes to penalty area per 90":38,"Deep completions per 90":33,"Smart passes per 90":57,"Accurate crosses, %":67,"Goal conversion, %":88},"gp":{"Goals per 90":99,"xG per 90":100,"Shots per 90":99,"Shots on target, %":85,"xA per 90":36,"Key passes per 90":29,"Crosses per 90":39,"Dribbles per 90":48,"Successful dribbles, %":90,"Offensive duels per 90":37,"Offensive duels won, %":68,"Touches in box per 90":95,"Progressive runs per 90":40,"Passes per 90":8,"Accurate passes, %":17,"Long passes per 90":26,"Accurate long passes, %":76,"Progressive passes per 90":35,"Accurate progressive passes, %":80,"Forward passes per 90":15,"Accurate forward passes, %":73,"Passes to final third per 90":30,"Passes to penalty area per 90":36,"Deep completions per 90":26,"Smart passes per 90":58,"Accurate crosses, %":77,"Goal conversion, %":83},"r":[{"key":"Crosses per 90","label":"Crosses /90","value":1,"percentile":40,"invert":false},{"key":"Accurate crosses, %","label":"Cross Success %","value":41.67,"percentile":67,"invert":false},{"key":"Goals per 90","label":"Goals /90","value":1,"percentile":99,"invert":false},{"key":"Shots per 90","label":"Shots /90","value":4.07,"percentile":97,"invert":false},{"key":"Shots on target, %","label":"Shots on Target %","value":53.06,"percentile":81,"invert":false},{"key":"Goal conversion, %","label":"Goal Conversion %","value":24.49,"percentile":88,"invert":false},{"key":"Touches in box per 90","label":"Box Touches /90","value":5.06,"percentile":95,"invert":false},{"key":"Key passes per 90","label":"Key Passes /90","value":0.25,"percentile":34,"invert":false},{"key":"Passes to final third per 90","label":"Final Third Passes /90","value":1.41,"percentile":26,"invert":false},{"key":"Dribbles per 90","label":"Dribbles /90","value":2.32,"percentile":37,"invert":false},{"key":"Successful dribbles, %","label":"Dribble Success %","value":67.86,"percentile":81,"invert":false}]}