{"id":5665,"n":"Bryan Róchez","sn":"B. Róchez","cl":"Leixões SC","tm":"Leixões","pos":"Centre-Forward","pg":"FW","age":31,"min":1146,"mp":19,"comp":"Portugal. Segunda Liga","lg":"Portugal Liga 2","mv":"€175k","mvn":175000,"nat":["Honduras"],"dob":"01/01/1995 (31)","pid":"333199","m":{"Goals per 90":0.47,"xG per 90":0.29,"Shots per 90":1.49,"Shots on target, %":42.11,"Assists per 90":0.16,"xA per 90":0.09,"Key passes per 90":0.55,"Crosses per 90":0.24,"Dribbles per 90":1.26,"Successful dribbles, %":37.5,"Offensive duels per 90":8.01,"Offensive duels won, %":31.37,"Touches in box per 90":2.91,"Progressive runs per 90":0.71,"Passes per 90":17.51,"Accurate passes, %":71.75,"Long passes per 90":0.39,"Accurate long passes, %":40,"Progressive passes per 90":2.2,"Accurate progressive passes, %":71.43,"Forward passes per 90":4.16,"Accurate forward passes, %":62.26,"Passes to final third per 90":2.51,"Passes to penalty area per 90":0.55,"Deep completions per 90":0.86,"Accurate crosses, %":33.33,"Goal conversion, %":31.58},"p":{"Goals per 90":95,"xG per 90":77,"Shots per 90":38,"Shots on target, %":65,"Assists per 90":62,"xA per 90":66,"Key passes per 90":77,"Crosses per 90":4,"Dribbles per 90":18,"Successful dribbles, %":12,"Offensive duels per 90":41,"Offensive duels won, %":26,"Touches in box per 90":65,"Progressive runs per 90":22,"Passes per 90":49,"Accurate passes, %":47,"Long passes per 90":15,"Accurate long passes, %":26,"Progressive passes per 90":42,"Accurate progressive passes, %":52,"Forward passes per 90":43,"Accurate forward passes, %":49,"Passes to final third per 90":72,"Passes to penalty area per 90":20,"Deep completions per 90":71,"Accurate crosses, %":50,"Goal conversion, %":95},"gp":{"Goals per 90":84,"xG per 90":64,"Shots per 90":33,"Shots on target, %":58,"Assists per 90":56,"xA per 90":55,"Key passes per 90":75,"Crosses per 90":6,"Dribbles per 90":22,"Successful dribbles, %":13,"Offensive duels per 90":38,"Offensive duels won, %":34,"Touches in box per 90":51,"Progressive runs per 90":23,"Passes per 90":36,"Accurate passes, %":42,"Long passes per 90":13,"Accurate long passes, %":27,"Progressive passes per 90":40,"Accurate progressive passes, %":57,"Forward passes per 90":40,"Accurate forward passes, %":57,"Passes to final third per 90":70,"Passes to penalty area per 90":9,"Deep completions per 90":58,"Accurate crosses, %":56,"Goal conversion, %":93},"r":[{"key":"Crosses per 90","label":"Crosses /90","value":0.24,"percentile":4,"invert":false},{"key":"Accurate crosses, %","label":"Cross Success %","value":33.33,"percentile":50,"invert":false},{"key":"Goals per 90","label":"Goals /90","value":0.47,"percentile":95,"invert":false},{"key":"Shots per 90","label":"Shots /90","value":1.49,"percentile":38,"invert":false},{"key":"Shots on target, %","label":"Shots on Target %","value":42.11,"percentile":65,"invert":false},{"key":"Goal conversion, %","label":"Goal Conversion %","value":31.58,"percentile":95,"invert":false},{"key":"Touches in box per 90","label":"Box Touches /90","value":2.91,"percentile":65,"invert":false},{"key":"Assists per 90","label":"Assists /90","value":0.16,"percentile":62,"invert":false},{"key":"Key passes per 90","label":"Key Passes /90","value":0.55,"percentile":77,"invert":false},{"key":"Passes to final third per 90","label":"Final Third Passes /90","value":2.51,"percentile":72,"invert":false},{"key":"Dribbles per 90","label":"Dribbles /90","value":1.26,"percentile":18,"invert":false},{"key":"Successful dribbles, %","label":"Dribble Success %","value":37.5,"percentile":12,"invert":false}]}