{"id":6093,"n":"Matteo Colombo","sn":"M. Colombo","cl":"US Pianese","tm":"Pianese","pos":"Defensive Midfield","pg":"DM","age":21,"min":338,"mp":9,"comp":"Italy. Serie C","lg":"Italy Serie C Group B","mv":"€150k","mvn":150000,"nat":["Italy"],"dob":"09/03/2004 (21)","pid":"814015","m":{"xG per 90":0.05,"Shots per 90":1.07,"Shots on target, %":25,"xA per 90":0.04,"Key passes per 90":0.53,"Crosses per 90":2.13,"Dribbles per 90":2.4,"Successful dribbles, %":77.78,"Offensive duels per 90":6.39,"Offensive duels won, %":50,"Touches in box per 90":1.6,"Progressive runs per 90":1.6,"Progressive passes per 90":6.92,"Accurate progressive passes, %":80.77,"Passes to final third per 90":7.19,"Passes to penalty area per 90":2.4,"Deep completions per 90":0.8},"p":{"xG per 90":54,"Shots per 90":79,"Shots on target, %":46,"xA per 90":40,"Key passes per 90":94,"Crosses per 90":96,"Dribbles per 90":97,"Successful dribbles, %":87,"Offensive duels per 90":91,"Offensive duels won, %":69,"Touches in box per 90":93,"Progressive runs per 90":93,"Progressive passes per 90":43,"Accurate progressive passes, %":86,"Passes to final third per 90":44,"Passes to penalty area per 90":83,"Deep completions per 90":79},"gp":{"xG per 90":47,"Shots per 90":73,"Shots on target, %":37,"xA per 90":48,"Key passes per 90":94,"Crosses per 90":97,"Dribbles per 90":96,"Successful dribbles, %":83,"Offensive duels per 90":87,"Offensive duels won, %":71,"Touches in box per 90":91,"Progressive runs per 90":88,"Progressive passes per 90":63,"Accurate progressive passes, %":88,"Passes to final third per 90":66,"Passes to penalty area per 90":86,"Deep completions per 90":77},"r":[]}