{"id":6270,"n":"Nikola Zvrko","sn":"N. Zvrko","cl":"OFK Petrovac","tm":"Petrovac","pos":"Attacking Midfield","pg":"AM","age":30,"min":623,"mp":13,"comp":"Montenegro. First League","lg":"Montenegro 1. CFL","mv":"€150k","mvn":150000,"nat":["Montenegro"],"dob":"07/03/1995 (30)","pid":"319484","m":{"xG per 90":0.03,"Shots per 90":0.72,"Shots on target, %":60,"Assists per 90":0.14,"xA per 90":0.02,"Key passes per 90":0.29,"Crosses per 90":2.17,"Dribbles per 90":3.47,"Successful dribbles, %":45.83,"Offensive duels per 90":7.08,"Offensive duels won, %":34.69,"Touches in box per 90":1.16,"Progressive runs per 90":2.02,"Defensive duels per 90":5.63,"Defensive duels won, %":66.67,"Aerial duels per 90":0.72,"Aerial duels won, %":20,"Interceptions per 90":3.03,"Successful defensive actions per 90":7.08,"Sliding tackles per 90":0.29,"Fouls per 90":0.72,"Passes per 90":24.41,"Accurate passes, %":78.7,"Long passes per 90":1.01,"Accurate long passes, %":71.43,"Progressive passes per 90":3.9,"Accurate progressive passes, %":81.48,"Forward passes per 90":6.79,"Accurate forward passes, %":65.96,"Passes to final third per 90":1.59,"Passes to penalty area per 90":2.02,"Deep completions per 90":0.58,"Smart passes per 90":0.14},"p":{"xG per 90":15,"Shots per 90":21,"Shots on target, %":75,"Assists per 90":63,"xA per 90":7,"Key passes per 90":45,"Crosses per 90":88,"Dribbles per 90":64,"Successful dribbles, %":40,"Offensive duels per 90":31,"Offensive duels won, %":26,"Touches in box per 90":31,"Progressive runs per 90":50,"Defensive duels per 90":47,"Defensive duels won, %":75,"Aerial duels per 90":3,"Aerial duels won, %":8,"Interceptions per 90":69,"Successful defensive actions per 90":64,"Sliding tackles per 90":44,"Fouls per 90":86,"Passes per 90":21,"Accurate passes, %":56,"Long passes per 90":3,"Accurate long passes, %":97,"Progressive passes per 90":13,"Accurate progressive passes, %":92,"Forward passes per 90":21,"Accurate forward passes, %":62,"Passes to final third per 90":3,"Passes to penalty area per 90":34,"Deep completions per 90":24,"Smart passes per 90":17},"gp":{"xG per 90":6,"Shots per 90":9,"Shots on target, %":94,"Assists per 90":45,"xA per 90":5,"Key passes per 90":29,"Crosses per 90":73,"Dribbles per 90":75,"Successful dribbles, %":25,"Offensive duels per 90":45,"Offensive duels won, %":28,"Touches in box per 90":21,"Progressive runs per 90":72,"Defensive duels per 90":61,"Defensive duels won, %":83,"Aerial duels per 90":4,"Aerial duels won, %":13,"Interceptions per 90":74,"Successful defensive actions per 90":77,"Sliding tackles per 90":54,"Fouls per 90":80,"Passes per 90":32,"Accurate passes, %":61,"Long passes per 90":14,"Accurate long passes, %":94,"Progressive passes per 90":36,"Accurate progressive passes, %":82,"Forward passes per 90":30,"Accurate forward passes, %":51,"Passes to final third per 90":8,"Passes to penalty area per 90":41,"Deep completions per 90":22,"Smart passes per 90":34},"r":[{"key":"Key passes per 90","label":"Chances Created /90","value":0.29,"percentile":45,"invert":false},{"key":"xG per 90","label":"xG /90","value":0.03,"percentile":15,"invert":false},{"key":"xA per 90","label":"xA /90","value":0.02,"percentile":7,"invert":false},{"key":"Successful dribbles, %","label":"Dribble Success %","value":45.83,"percentile":40,"invert":false},{"key":"Dribbles per 90","label":"Dribbles /90","value":3.47,"percentile":64,"invert":false},{"key":"Shots on target, %","label":"Shots on Target %","value":60,"percentile":75,"invert":false},{"key":"Progressive runs per 90","label":"Progressive Runs /90","value":2.02,"percentile":50,"invert":false}]}