{"id":78,"n":"Kacper Trelowski","sn":"K. Trelowski","cl":"Raków Częstochowa","tm":"Raków Częstochowa","pos":"Goalkeeper","pg":"GK","age":22,"min":1107,"mp":11,"comp":"Poland. Ekstraklasa","lg":"Poland Ekstraklasa","mv":"€4.00m","mvn":4000000,"nat":["Poland"],"dob":"19/08/2003 (22)","pid":"720120","m":{"Aerial duels per 90":0.08,"Aerial duels won, %":100,"Interceptions per 90":0.33,"Successful defensive actions per 90":0.41,"Sliding tackles per 90":0.08,"Passes per 90":20.24,"Accurate passes, %":84.34,"Long passes per 90":7.56,"Accurate long passes, %":62.37,"Progressive passes per 90":5.04,"Accurate progressive passes, %":77.42,"Forward passes per 90":10.89,"Accurate forward passes, %":71.64,"Passes to final third per 90":2.28,"Passes to penalty area per 90":0.08,"Deep completions per 90":0.08},"p":{"Aerial duels per 90":2,"Aerial duels won, %":69,"Interceptions per 90":6,"Successful defensive actions per 90":6,"Passes per 90":44,"Accurate passes, %":54,"Long passes per 90":52,"Accurate long passes, %":48,"Progressive passes per 90":40,"Accurate progressive passes, %":77,"Forward passes per 90":48,"Accurate forward passes, %":63,"Passes to final third per 90":60,"Passes to penalty area per 90":9,"Deep completions per 90":75},"gp":{"Aerial duels per 90":1,"Aerial duels won, %":70,"Interceptions per 90":1,"Successful defensive actions per 90":1,"Sliding tackles per 90":66,"Passes per 90":50,"Accurate passes, %":50,"Long passes per 90":51,"Accurate long passes, %":47,"Progressive passes per 90":39,"Accurate progressive passes, %":76,"Forward passes per 90":47,"Accurate forward passes, %":34,"Passes to final third per 90":65,"Passes to penalty area per 90":18,"Deep completions per 90":60},"r":[{"key":"Accurate passes, %","label":"Pass Accuracy %","value":84.34,"percentile":54,"invert":false}]}