{"id":8171,"n":"Genc Hamiti","sn":"G. Hamiti","cl":"KF Drenica","tm":"Drenica Skënderaj","pos":"Attacking Midfield","pg":"AM","age":32,"min":1452,"mp":15,"comp":"Kosovo. Superliga","lg":"Kosovo Superliga","mv":"€75k","mvn":75000,"nat":["Kosovo"],"dob":"21/09/1993 (32)","pid":"458360","m":{"xA per 90":0.09,"Key passes per 90":0.06,"Defensive duels per 90":6.45,"Defensive duels won, %":64.42,"Aerial duels per 90":2.29,"Aerial duels won, %":24.32,"Interceptions per 90":2.42,"Successful defensive actions per 90":6.82,"Sliding tackles per 90":0.25,"Fouls per 90":1.24,"Passes per 90":37.13,"Accurate passes, %":80.63,"Long passes per 90":2.48,"Accurate long passes, %":50,"Progressive passes per 90":6.14,"Accurate progressive passes, %":72.73,"Forward passes per 90":12.4,"Accurate forward passes, %":74,"Passes to final third per 90":6.57,"Passes to penalty area per 90":1.55,"Deep completions per 90":0.5,"Smart passes per 90":0.31,"Shots blocked per 90":0.06},"p":{"xA per 90":39,"Key passes per 90":6,"Defensive duels per 90":85,"Defensive duels won, %":65,"Aerial duels per 90":55,"Aerial duels won, %":15,"Interceptions per 90":55,"Successful defensive actions per 90":75,"Sliding tackles per 90":56,"Fouls per 90":65,"Passes per 90":95,"Accurate passes, %":75,"Long passes per 90":55,"Accurate long passes, %":45,"Progressive passes per 90":83,"Accurate progressive passes, %":28,"Forward passes per 90":95,"Accurate forward passes, %":75,"Passes to final third per 90":83,"Passes to penalty area per 90":28,"Deep completions per 90":6,"Smart passes per 90":70,"Shots blocked per 90":7},"gp":{"xA per 90":46,"Key passes per 90":0,"Defensive duels per 90":79,"Defensive duels won, %":75,"Aerial duels per 90":54,"Aerial duels won, %":20,"Interceptions per 90":53,"Successful defensive actions per 90":72,"Sliding tackles per 90":46,"Fouls per 90":46,"Passes per 90":83,"Accurate passes, %":73,"Long passes per 90":62,"Accurate long passes, %":49,"Progressive passes per 90":81,"Accurate progressive passes, %":46,"Forward passes per 90":85,"Accurate forward passes, %":84,"Passes to final third per 90":88,"Passes to penalty area per 90":24,"Deep completions per 90":16,"Smart passes per 90":73,"Shots blocked per 90":7},"r":[{"key":"Key passes per 90","label":"Chances Created /90","value":0.06,"percentile":6,"invert":false},{"key":"xA per 90","label":"xA /90","value":0.09,"percentile":39,"invert":false}]}