{"id":852,"n":"Moustapha Cissé","sn":"M. Cissé","cl":"Atalanta U23","tm":"Atalanta U23","pos":"Centre-Forward","pg":"FW","age":22,"min":1096,"mp":20,"comp":"Italy. Serie C","lg":"Italy Serie C Group C","mv":"€800k","mvn":800000,"nat":["Guinea"],"dob":"14/09/2003 (22)","pid":"988862","m":{"Goals per 90":0.08,"xG per 90":0.29,"Shots per 90":2.38,"Shots on target, %":20.69,"Assists per 90":0.25,"xA per 90":0.16,"Key passes per 90":0.82,"Crosses per 90":0.74,"Dribbles per 90":1.64,"Successful dribbles, %":55,"Offensive duels per 90":8.46,"Offensive duels won, %":26.21,"Touches in box per 90":4.76,"Progressive runs per 90":0.82,"Passes per 90":16.42,"Accurate passes, %":82,"Long passes per 90":0.33,"Accurate long passes, %":75,"Progressive passes per 90":1.64,"Accurate progressive passes, %":70,"Forward passes per 90":2.71,"Accurate forward passes, %":78.79,"Passes to final third per 90":1.15,"Passes to penalty area per 90":1.31,"Deep completions per 90":1.15,"Smart passes per 90":0.08,"Accurate crosses, %":33.33,"Goal conversion, %":3.45},"p":{"Goals per 90":6,"xG per 90":70,"Shots per 90":79,"Shots on target, %":8,"Assists per 90":83,"xA per 90":88,"Key passes per 90":95,"Crosses per 90":41,"Dribbles per 90":39,"Successful dribbles, %":58,"Offensive duels per 90":39,"Offensive duels won, %":17,"Touches in box per 90":98,"Progressive runs per 90":37,"Passes per 90":39,"Accurate passes, %":93,"Long passes per 90":10,"Accurate long passes, %":86,"Progressive passes per 90":36,"Accurate progressive passes, %":56,"Forward passes per 90":19,"Accurate forward passes, %":96,"Passes to final third per 90":26,"Passes to penalty area per 90":50,"Deep completions per 90":87,"Smart passes per 90":32,"Accurate crosses, %":58,"Goal conversion, %":2},"gp":{"Goals per 90":4,"xG per 90":64,"Shots per 90":77,"Shots on target, %":7,"Assists per 90":81,"xA per 90":82,"Key passes per 90":92,"Crosses per 90":29,"Dribbles per 90":31,"Successful dribbles, %":58,"Offensive duels per 90":44,"Offensive duels won, %":15,"Touches in box per 90":92,"Progressive runs per 90":28,"Passes per 90":30,"Accurate passes, %":92,"Long passes per 90":9,"Accurate long passes, %":90,"Progressive passes per 90":26,"Accurate progressive passes, %":53,"Forward passes per 90":15,"Accurate forward passes, %":96,"Passes to final third per 90":20,"Passes to penalty area per 90":38,"Deep completions per 90":79,"Smart passes per 90":20,"Accurate crosses, %":56,"Goal conversion, %":1},"r":[{"key":"Crosses per 90","label":"Crosses /90","value":0.74,"percentile":41,"invert":false},{"key":"Accurate crosses, %","label":"Cross Success %","value":33.33,"percentile":58,"invert":false},{"key":"Goals per 90","label":"Goals /90","value":0.08,"percentile":6,"invert":false},{"key":"Shots per 90","label":"Shots /90","value":2.38,"percentile":79,"invert":false},{"key":"Shots on target, %","label":"Shots on Target %","value":20.69,"percentile":8,"invert":false},{"key":"Goal conversion, %","label":"Goal Conversion %","value":3.45,"percentile":2,"invert":false},{"key":"Touches in box per 90","label":"Box Touches /90","value":4.76,"percentile":98,"invert":false},{"key":"Assists per 90","label":"Assists /90","value":0.25,"percentile":83,"invert":false},{"key":"Key passes per 90","label":"Key Passes /90","value":0.82,"percentile":95,"invert":false},{"key":"Passes to final third per 90","label":"Final Third Passes /90","value":1.15,"percentile":26,"invert":false},{"key":"Dribbles per 90","label":"Dribbles /90","value":1.64,"percentile":39,"invert":false},{"key":"Successful dribbles, %","label":"Dribble Success %","value":55,"percentile":58,"invert":false}]}