{"id":8604,"n":"Vanja Apostolovski","sn":"V. Apostolovski","cl":"FK Kabel Novi Sad","tm":"Kabel Novi Sad","pos":"Defensive Midfield","pg":"DM","age":21,"min":454,"mp":10,"comp":"Serbia. Prva Liga","lg":"Serbia Prva Liga","mv":"€50k","mvn":50000,"nat":["Serbia","North Macedonia"],"dob":"10/07/2004 (21)","pid":"849652","m":{"xA per 90":0.02,"Key passes per 90":0.2,"Defensive duels per 90":6.94,"Defensive duels won, %":57.14,"Aerial duels per 90":3.37,"Aerial duels won, %":58.82,"Interceptions per 90":2.58,"Successful defensive actions per 90":7.73,"Sliding tackles per 90":1.19,"Fouls per 90":2.18,"Passes per 90":23,"Accurate passes, %":80.17,"Long passes per 90":1.98,"Accurate long passes, %":50,"Progressive passes per 90":2.58,"Accurate progressive passes, %":69.23,"Forward passes per 90":6.34,"Accurate forward passes, %":65.63,"Passes to final third per 90":2.38,"Passes to penalty area per 90":1.98,"Deep completions per 90":1.59},"p":{"xA per 90":29,"Key passes per 90":60,"Defensive duels per 90":60,"Defensive duels won, %":46,"Aerial duels per 90":54,"Aerial duels won, %":83,"Interceptions per 90":7,"Successful defensive actions per 90":31,"Sliding tackles per 90":95,"Fouls per 90":29,"Passes per 90":6,"Accurate passes, %":72,"Long passes per 90":9,"Accurate long passes, %":65,"Progressive passes per 90":1,"Accurate progressive passes, %":67,"Forward passes per 90":4,"Accurate forward passes, %":67,"Passes to final third per 90":4,"Passes to penalty area per 90":82,"Deep completions per 90":99},"gp":{"xA per 90":25,"Key passes per 90":51,"Defensive duels per 90":67,"Defensive duels won, %":26,"Aerial duels per 90":71,"Aerial duels won, %":82,"Interceptions per 90":10,"Successful defensive actions per 90":37,"Sliding tackles per 90":96,"Fouls per 90":13,"Passes per 90":4,"Accurate passes, %":33,"Long passes per 90":10,"Accurate long passes, %":40,"Progressive passes per 90":2,"Accurate progressive passes, %":41,"Forward passes per 90":2,"Accurate forward passes, %":31,"Passes to final third per 90":2,"Passes to penalty area per 90":75,"Deep completions per 90":98},"r":[{"key":"Accurate passes, %","label":"Pass Accuracy %","value":80.17,"percentile":72,"invert":false},{"key":"Defensive duels won, %","label":"Defensive Challenge %","value":57.14,"percentile":46,"invert":false},{"key":"Successful defensive actions per 90","label":"Ball Recoveries /90","value":7.73,"percentile":31,"invert":false},{"key":"Passes per 90","label":"Passes /90","value":23,"percentile":6,"invert":false},{"key":"Accurate long passes, %","label":"Long Ball Accuracy %","value":50,"percentile":65,"invert":false},{"key":"Aerial duels won, %","label":"Aerial Challenge %","value":58.82,"percentile":83,"invert":false},{"key":"Fouls per 90","label":"Fouls /90","value":2.18,"percentile":29,"invert":true}]}