{"id":9355,"n":"Duarte Carvalho","sn":"Duarte Carvalho","cl":"USC Paredes","tm":"Paredes","pos":"Central Midfield","pg":"CM","age":23,"min":358,"mp":10,"comp":"Portugal. Liga 3","lg":"Portugal Liga 3","mv":"-","mvn":0,"nat":["Portugal"],"dob":"30/05/2002 (23)","pid":"742484","m":{"Goals per 90":0.25,"xG per 90":0.11,"Shots per 90":3.02,"Shots on target, %":16.67,"xA per 90":0.1,"Crosses per 90":1.51,"Dribbles per 90":3.02,"Successful dribbles, %":50,"Offensive duels per 90":11.56,"Offensive duels won, %":39.13,"Touches in box per 90":2.26,"Progressive runs per 90":1.76,"Goal conversion, %":8.33},"p":{"Goals per 90":73,"xG per 90":63,"Shots per 90":99,"Shots on target, %":12,"xA per 90":71,"Crosses per 90":75,"Dribbles per 90":91,"Successful dribbles, %":41,"Offensive duels per 90":94,"Offensive duels won, %":47,"Touches in box per 90":96,"Progressive runs per 90":88,"Goal conversion, %":13},"gp":{"Goals per 90":82,"xG per 90":66,"Shots per 90":100,"Shots on target, %":9,"xA per 90":66,"Crosses per 90":62,"Dribbles per 90":86,"Successful dribbles, %":32,"Offensive duels per 90":95,"Offensive duels won, %":36,"Touches in box per 90":85,"Progressive runs per 90":78,"Goal conversion, %":30},"r":[]}