{"id":9529,"n":"Loïc Mesanvi","sn":"L. Mesanvi","cl":"Minnesota United FC 2","tm":"-","pos":"Left Winger","pg":"FW","age":22,"min":1948,"mp":22,"comp":"United States. MLS Next Pro","lg":"MLS Next Pro","mv":"-","mvn":0,"nat":["Togo","United States"],"dob":"Jun 10, 2003","pid":"1042556","m":{"Goals per 90":0.18,"xG per 90":0.26,"Shots per 90":1.71,"Shots on target, %":51.35,"xA per 90":0.07,"Key passes per 90":0.23,"Crosses per 90":1.25,"Dribbles per 90":3.33,"Successful dribbles, %":45.83,"Offensive duels per 90":11.87,"Offensive duels won, %":31.52,"Touches in box per 90":4.02,"Progressive runs per 90":2.49,"Progressive passes per 90":3.19,"Accurate progressive passes, %":69.57,"Passes to final third per 90":2.31,"Passes to penalty area per 90":1.76,"Deep completions per 90":1.11,"Smart passes per 90":0.05,"Accurate crosses, %":33.33,"Goal conversion, %":10.81},"p":{"Goals per 90":14,"xG per 90":40,"Shots per 90":32,"Shots on target, %":78,"xA per 90":30,"Key passes per 90":17,"Crosses per 90":52,"Dribbles per 90":66,"Successful dribbles, %":21,"Offensive duels per 90":74,"Offensive duels won, %":22,"Touches in box per 90":64,"Progressive runs per 90":81,"Progressive passes per 90":63,"Accurate progressive passes, %":42,"Passes to final third per 90":71,"Passes to penalty area per 90":60,"Deep completions per 90":71,"Smart passes per 90":5,"Accurate crosses, %":43,"Goal conversion, %":22},"gp":{"Goals per 90":27,"xG per 90":57,"Shots per 90":45,"Shots on target, %":83,"xA per 90":44,"Key passes per 90":25,"Crosses per 90":47,"Dribbles per 90":67,"Successful dribbles, %":29,"Offensive duels per 90":81,"Offensive duels won, %":35,"Touches in box per 90":82,"Progressive runs per 90":82,"Progressive passes per 90":60,"Accurate progressive passes, %":52,"Passes to final third per 90":65,"Passes to penalty area per 90":53,"Deep completions per 90":77,"Smart passes per 90":4,"Accurate crosses, %":56,"Goal conversion, %":29},"r":[{"key":"Crosses per 90","label":"Crosses /90","value":1.25,"percentile":52,"invert":false},{"key":"Accurate crosses, %","label":"Cross Success %","value":33.33,"percentile":43,"invert":false},{"key":"Goals per 90","label":"Goals /90","value":0.18,"percentile":14,"invert":false},{"key":"Shots per 90","label":"Shots /90","value":1.71,"percentile":32,"invert":false},{"key":"Shots on target, %","label":"Shots on Target %","value":51.35,"percentile":78,"invert":false},{"key":"Goal conversion, %","label":"Goal Conversion %","value":10.81,"percentile":22,"invert":false},{"key":"Touches in box per 90","label":"Box Touches /90","value":4.02,"percentile":64,"invert":false},{"key":"Key passes per 90","label":"Key Passes /90","value":0.23,"percentile":17,"invert":false},{"key":"Passes to final third per 90","label":"Final Third Passes /90","value":2.31,"percentile":71,"invert":false},{"key":"Dribbles per 90","label":"Dribbles /90","value":3.33,"percentile":66,"invert":false},{"key":"Successful dribbles, %","label":"Dribble Success %","value":45.83,"percentile":21,"invert":false}]}