{"id":9679,"n":"Yoann Abasq","sn":"Y. Abasq","cl":"RC Grasse","tm":"Grasse","pos":"Centre-Back","pg":"CB","age":24,"min":765,"mp":18,"comp":"France. National 2","lg":"France National 2 Group C","mv":"-","mvn":0,"nat":["Cameroon","France"],"dob":"20/11/2001 (24)","pid":"944182","m":{"xG per 90":0.02,"Shots per 90":0.12,"Shots on target, %":100,"xA per 90":0.04,"Crosses per 90":1.76,"Dribbles per 90":1.41,"Successful dribbles, %":58.33,"Offensive duels per 90":4.12,"Offensive duels won, %":42.86,"Touches in box per 90":0.24,"Progressive runs per 90":0.82,"Accurate crosses, %":33.33},"p":{"xG per 90":15,"Shots per 90":5,"Shots on target, %":97,"xA per 90":73,"Crosses per 90":93,"Dribbles per 90":91,"Successful dribbles, %":40,"Offensive duels per 90":87,"Offensive duels won, %":44,"Touches in box per 90":10,"Progressive runs per 90":53,"Accurate crosses, %":39},"gp":{"xG per 90":17,"Shots per 90":6,"Shots on target, %":97,"xA per 90":77,"Crosses per 90":96,"Dribbles per 90":97,"Successful dribbles, %":35,"Offensive duels per 90":97,"Offensive duels won, %":37,"Touches in box per 90":9,"Progressive runs per 90":55,"Accurate crosses, %":30},"r":[]}