{"id":9863,"n":"Onesime Zimuangana","sn":"O. Zimuangana","cl":"Helmond Sport","tm":"Helmond Sport","pos":"Right Winger","pg":"FW","age":19,"min":216,"mp":5,"comp":"Netherlands. Eerste Divisie","lg":"Netherlands Eerste Divisie","mv":"-","mvn":0,"nat":["Netherlands","DR Congo"],"dob":"05/03/2006 (19)","pid":"864124","m":{"Passes per 90":18.75,"Accurate passes, %":57.78,"Long passes per 90":1.67,"Accurate long passes, %":75,"Forward passes per 90":5,"Accurate forward passes, %":50},"p":{"Passes per 90":38,"Accurate passes, %":2,"Long passes per 90":75,"Accurate long passes, %":97,"Forward passes per 90":55,"Accurate forward passes, %":15},"gp":{"Passes per 90":44,"Accurate passes, %":2,"Long passes per 90":69,"Accurate long passes, %":90,"Forward passes per 90":54,"Accurate forward passes, %":16},"r":[]}