{"id":9883,"n":"Jahmarie Nolan","sn":"J. Nolan","cl":"Toronto FC II","tm":"Toronto II","pos":"Striker","pg":"FW","age":16,"min":1031,"mp":19,"comp":"United States. MLS Next Pro","lg":"MLS Next Pro","mv":"-","mvn":0,"nat":["Jamaica"],"dob":"11/11/2009 (16)","pid":"1325674","m":{"Assists per 90":0.17,"xA per 90":0.09,"Key passes per 90":0.26,"Progressive passes per 90":1.66,"Accurate progressive passes, %":78.95,"Passes to final third per 90":2.01,"Passes to penalty area per 90":0.96,"Deep completions per 90":0.61,"Smart passes per 90":0.09},"p":{"Assists per 90":46,"xA per 90":43,"Key passes per 90":23,"Progressive passes per 90":30,"Accurate progressive passes, %":73,"Passes to final third per 90":61,"Passes to penalty area per 90":30,"Deep completions per 90":30,"Smart passes per 90":27},"gp":{"Assists per 90":59,"xA per 90":55,"Key passes per 90":31,"Progressive passes per 90":27,"Accurate progressive passes, %":80,"Passes to final third per 90":55,"Passes to penalty area per 90":25,"Deep completions per 90":36,"Smart passes per 90":26},"r":[{"key":"Assists per 90","label":"Assists /90","value":0.17,"percentile":46,"invert":false},{"key":"Key passes per 90","label":"Key Passes /90","value":0.26,"percentile":23,"invert":false},{"key":"Passes to final third per 90","label":"Final Third Passes /90","value":2.01,"percentile":61,"invert":false}]}